feizhu_chat_client/__init__.py
feizhu_chat_client/main.py
feizhu_chat_client-0.1.3.dist-info/METADATA
feizhu_chat_client-0.1.3.dist-info/WHEEL
feizhu_chat_client-0.1.3.dist-info/entry_points.txt
feizhu_chat_client-0.1.3.dist-info/top_level.txt
feizhu_chat_client-0.1.3.dist-info/RECORD
