Metadata-Version: 2.1
Name: feizhu_chat_client
Version: 0.1.3
Summary: A simple WebSocket chat client
Home-page: https://github.com/yourusername/websocket-chat
Author: Your Name
Author-email: your.email@example.com
Classifier: Programming Language :: Python :: 3
Classifier: License :: OSI Approved :: MIT License
Classifier: Operating System :: OS Independent
Requires-Dist: websocket-client
